gFunctionDatabase/HDPEPipeDimensions.json
gFunctionDatabase/__init__.py
gFunctionDatabase/coordinates.py
gFunctionDatabase/featurerecognition.py
gFunctionDatabase/fileio.py
gFunctionDatabase/pipes.py
gFunctionDatabase/platform_specific.py
gFunctionDatabase/statistics.py
gFunctionDatabase/utilities.py
gFunctionDatabase/Data/C_configurations_5m.json
gFunctionDatabase/Data/L_configurations_5m.json
gFunctionDatabase/Data/LopU_configurations_5m.json
gFunctionDatabase/Data/Open_configurations_5m.json
gFunctionDatabase/Data/U_configurations_5m.json
gFunctionDatabase/Data/__init__.py
gFunctionDatabase/Data/available.py
gFunctionDatabase/Data/rectangle_5m.json
gFunctionDatabase/Data/zoned_rectangle_5m.json
gFunctionDatabase/General/__init__.py
gFunctionDatabase/General/fileio.py
gFunctionDatabase/General/platform_specific.py
gFunctionDatabase/Management/__init__.py
gFunctionDatabase/Management/application.py
gFunctionDatabase/Management/data_definition.py
gFunctionDatabase/Management/retrieval.py
gFunctionDatabase/Management/update.py
pygfunction/__init__.py
pygfunction/boreholes.py
pygfunction/gfunction.py
pygfunction/heat_transfer.py
pygfunction/load_aggregation.py
pygfunction/media.py
pygfunction/networks.py
pygfunction/pipes.py
pygfunction/utilities.py
pygfunction/examples/__init__.py
pygfunction/examples/bore_field_thermal_resistance.py
pygfunction/examples/comparison_load_aggregation.py
pygfunction/examples/custom_bore_field.py
pygfunction/examples/custom_bore_field_from_file.py
pygfunction/examples/custom_borehole.py
pygfunction/examples/equal_inlet_temperature.py
pygfunction/examples/fluid_temperature.py
pygfunction/examples/fluid_temperature_multiple_boreholes.py
pygfunction/examples/load_aggregation.py
pygfunction/examples/mixed_inlet_conditions.py
pygfunction/examples/multiple_independent_Utubes.py
pygfunction/examples/multipole_temperature.py
pygfunction/examples/regular_bore_field.py
pygfunction/examples/unequal_segments.py
gFunctionDatabase-0.3.dist-info/LICENSE
gFunctionDatabase-0.3.dist-info/METADATA
gFunctionDatabase-0.3.dist-info/WHEEL
gFunctionDatabase-0.3.dist-info/top_level.txt
gFunctionDatabase-0.3.dist-info/RECORD
