Metadata-Version: 2.1
Name: gFunctionDatabase
Version: 0.3
Summary: A g-function database with a database management system for data retrieval, updates and application to be used ingeothermal ground heat exchanger design.
Home-page: https://github.com/j-c-cook/gFunctionDatabase
Author: Jack C. Cook
Author-email: jack.cook@okstate.edu
License: UNKNOWN
Download-URL: https://github.com/j-c-cook/gFunctionDatabase/archive/v0.3.tar.gz
Platform: UNKNOWN
License-File: LICENSE
Requires-Dist: matplotlib (>=3.3.4)
Requires-Dist: numpy (>=1.19.2)
Requires-Dist: Pillow (>=8.1.0)
Requires-Dist: scipy (>=1.6.2)
Requires-Dist: pandas (>=1.3.2)
Requires-Dist: natsort (>=7.1.1)
